Metadata-Version: 2.1
Name: oneNeuron-pypi-activevj
Version: 0.0.1
Summary: Its an implementation of Perceptron
Home-page: https://github.com/activevj/oneNeuron_pypi
Author: activevj
Author-email: uservjkumar@gmail.com
License: UNKNOWN
Project-URL: Bug Tracker, https://github.com/activevj/oneNeuron_pypi/issues
Platform: UNKNOWN
Classifier: Programming Language :: Python :: 3
Classifier: License :: OSI Approved :: MIT License
Classifier: Operating System :: OS Independent
Requires-Python: >=3.7
License-File: LICENSE
Requires-Dist: numpy
Requires-Dist: tqdm
Requires-Dist: logging
